{
  "name": "Socio: Sheet → Fetch MP4 → Drive → Sheet",
  "description": "Prod URL is static — n8n Cloud blocks $env in expressions. For local API, temporarily set URL to http://127.0.0.1:8001/clip_download",
  "nodes": [
    {
      "parameters": {
        "pollTimes": { "item": [{ "mode": "everyMinute" }] },
        "documentId": {
          "__rl": true,
          "value": "1bjUzMcmFiejlVv_N2qFSCBUOYM4JgsG9ZGXMb482-6Y",
          "mode": "list"
        },
        "sheetName": { "__rl": true, "value": 4223526, "mode": "list" },
        "options": {}
      },
      "name": "Sheet new reel row",
      "type": "n8n-nodes-base.googleSheetsTrigger",
      "typeVersion": 1,
      "position": [-800, 0]
    },
    {
      "parameters": {
        "method": "POST",
        "url": "http://dr5o3ostqc3oreb2emg16fhk.72.60.205.36.sslip.io/clip_download",
        "authentication": "none",
        "sendHeaders": true,
        "specifyHeaders": "keypair",
        "headerParameters": {
          "parameters": [{ "name": "api-key", "value": "key789" }]
        },
        "sendBody": true,
        "contentType": "json",
        "specifyBody": "keypair",
        "bodyParameters": {
          "parameters": [
            { "name": "url", "value": "={{ $json.reel_url }}" },
            {
              "name": "filename",
              "value": "={{ String($('Sheet new reel row').item.json.ID) }}.mp4"
            }
          ]
        },
        "options": {
          "response": {
            "response": {
              "responseFormat": "file",
              "outputPropertyName": "raw_mp4",
              "neverError": true
            }
          }
        }
      },
      "name": "HTTP fetch reel MP4",
      "type": "n8n-nodes-base.httpRequest",
      "typeVersion": 4.4,
      "position": [-480, 0],
      "continueOnFail": true
    },
    {
      "parameters": {
        "conditions": {
          "options": {
            "caseSensitive": true,
            "leftValue": "",
            "typeValidation": "strict",
            "version": 2
          },
          "conditions": [
            {
              "id": "f0e30b01-d45e-4bd9-8b78-a3a0f5874fbe",
              "leftValue": "={{ !!$binary.raw_mp4 }}",
              "rightValue": "",
              "operator": {
                "type": "boolean",
                "operation": "true",
                "singleValue": true
              }
            }
          ],
          "combinator": "and"
        },
        "options": {}
      },
      "name": "IF fetch succeeded",
      "type": "n8n-nodes-base.if",
      "typeVersion": 2.2,
      "position": [-320, 0]
    },
    {
      "parameters": {
        "resource": "file",
        "operation": "upload",
        "inputDataFieldName": "raw_mp4",
        "name": "={{ $('Sheet new reel row').item.json.ID }}.mp4",
        "driveId": { "__rl": true, "value": "My Drive", "mode": "list" },
        "folderId": {
          "__rl": true,
          "value": "197FhyyD6c3pTZJ7n8Clkw7q6XlnSLxLj",
          "mode": "list",
          "cachedResultName": "video/raw"
        },
        "options": {}
      },
      "name": "Drive upload video to raw",
      "type": "n8n-nodes-base.googleDrive",
      "typeVersion": 3,
      "position": [-160, 0]
    },
    {
      "parameters": {
        "method": "POST",
        "url": "http://dr5o3ostqc3oreb2emg16fhk.72.60.205.36.sslip.io/extraction",
        "authentication": "none",
        "sendHeaders": true,
        "specifyHeaders": "keypair",
        "headerParameters": {
          "parameters": [{ "name": "api-key", "value": "key789" }]
        },
        "sendBody": false,
        "sendQuery": true,
        "specifyQuery": "keypair",
        "queryParameters": {
          "parameters": [
            {
              "name": "filename",
              "value": "={{ String($('Sheet new reel row').item.json.ID) }}.mp4"
            }
          ]
        },
        "options": {
          "response": {
            "response": {
              "responseFormat": "file",
              "outputPropertyName": "cropped_mp4",
              "neverError": true
            }
          }
        }
      },
      "name": "HTTP extraction (cropped)",
      "type": "n8n-nodes-base.httpRequest",
      "typeVersion": 4.4,
      "position": [0, 0],
      "continueOnFail": true
    },
    {
      "parameters": {
        "resource": "sheet",
        "operation": "appendOrUpdate",
        "documentId": {
          "__rl": true,
          "value": "1bjUzMcmFiejlVv_N2qFSCBUOYM4JgsG9ZGXMb482-6Y",
          "mode": "list"
        },
        "sheetName": { "__rl": true, "value": 4223526, "mode": "list" },
        "columns": {
          "mappingMode": "defineBelow",
          "value": {
            "ID": "={{ $('Sheet new reel row').item.json.ID }}",
            "processing_status": "In progress",
            "raw_gdrive_url": "={{ $('Drive upload video to raw').item.json.webViewLink }}"
          },
          "matchingColumns": ["ID"],
          "schema": [],
          "attemptToConvertTypes": false,
          "convertFieldsToString": false
        },
        "options": {}
      },
      "name": "Sheet update link and status",
      "type": "n8n-nodes-base.googleSheets",
      "typeVersion": 4.7,
      "position": [160, 0]
    }
  ],
  "connections": {
    "Sheet new reel row": {
      "main": [
        [{ "node": "HTTP fetch reel MP4", "type": "main", "index": 0 }]
      ]
    },
    "HTTP fetch reel MP4": {
      "main": [
        [{ "node": "IF fetch succeeded", "type": "main", "index": 0 }]
      ]
    },
    "IF fetch succeeded": {
      "main": [
        [{ "node": "Drive upload video to raw", "type": "main", "index": 0 }],
        []
      ]
    },
    "Drive upload video to raw": {
      "main": [
        [{ "node": "HTTP extraction (cropped)", "type": "main", "index": 0 }]
      ]
    },
    "HTTP extraction (cropped)": {
      "main": [
        [{ "node": "Sheet update link and status", "type": "main", "index": 0 }]
      ]
    }
  },
  "settings": { "executionOrder": "v1", "binaryMode": "separate" }
}
